setup.py
image_analogy/__init__.py
image_analogy/argparser.py
image_analogy/img_utils.py
image_analogy/main.py
image_analogy/optimizer.py
image_analogy/vgg16.py
image_analogy/losses/__init__.py
image_analogy/losses/analogy.py
image_analogy/losses/core.py
image_analogy/losses/mrf.py
image_analogy/losses/neural_style.py
image_analogy/losses/nnf.py
image_analogy/losses/patch_matcher.py
image_analogy/losses/patches.py
image_analogy/models/__init__.py
image_analogy/models/analogy.py
image_analogy/models/base.py
image_analogy/models/nnf.py
neural_image_analogies.egg-info/PKG-INFO
neural_image_analogies.egg-info/SOURCES.txt
neural_image_analogies.egg-info/dependency_links.txt
neural_image_analogies.egg-info/pbr.json
neural_image_analogies.egg-info/requires.txt
neural_image_analogies.egg-info/top_level.txt
scripts/make_image_analogy.py