Metadata-Version: 1.0
Name: neural-image-analogies
Version: 0.1.2
Summary: Generate image analogies with a deep neural network.
Home-page: https://github.com/awentzonline/image-analogies/
Author: Adam Wentz
Author-email: adam@adamwentz.com
License: UNKNOWN
Platform: UNKNOWN
